omie/__init__.py
omie/__main__.py
omie/client.py
omie/exceptions.py
omie/methods.py
omie/schemas.py
omie_python-0.0.1.dist-info/LICENSE
omie_python-0.0.1.dist-info/METADATA
omie_python-0.0.1.dist-info/WHEEL
omie_python-0.0.1.dist-info/entry_points.txt
omie_python-0.0.1.dist-info/top_level.txt
omie_python-0.0.1.dist-info/RECORD
