Metadata-Version: 2.1
Name: omie-python
Version: 0.0.1
Summary: Client for the Omie ERP API
Author-email: Lucas Schneider <lucasschneider.dev@gmail.com>
License: MIT License
Project-URL: Homepage, https://github.com/schneider8357/omie-python
Keywords: omie,api,client
Classifier: Programming Language :: Python :: 3
Classifier: License :: OSI Approved :: MIT License
Classifier: Operating System :: OS Independent
Requires-Python: >=3.9
License-File: LICENSE
Requires-Dist: cachetools ==5.3.3
Requires-Dist: openpyxl ==3.1.2
Requires-Dist: pandas ==2.2.2
Requires-Dist: pydantic ==2.7.1
Requires-Dist: python-dotenv ==1.0.1
Requires-Dist: requests ==2.31.0
Requires-Dist: typer ==0.12.3
